package_346234294/__init__.py
package_346234294/example.py
package_346234294-1.0.3.dist-info/METADATA
package_346234294-1.0.3.dist-info/WHEEL
package_346234294-1.0.3.dist-info/top_level.txt
package_346234294-1.0.3.dist-info/RECORD
