Metadata-Version: 2.4
Name: package_346234294
Version: 1.0.3
Summary: A package to demonstrate dependency confusion in a supplychain attack
Author-email: Liss <test@test.de>
Project-URL: Homepage, https://github.com/pypa/sampleproject
Project-URL: Issues, https://github.com/pypa/sampleproject/issues
Classifier: Programming Language :: Python :: 3
Classifier: Operating System :: OS Independent
Classifier: License :: OSI Approved :: MIT License
Requires-Python: >=3.8
